<?xml version="1.0" encoding="utf-8"?>
<Deployment xmlns="http://schemas.microsoft.com/windowsphone/2009/deployment" AppPlatformVersion="7.1">
  <App xmlns="" ProductID="{6bce3e09-bc72-4625-bfd2-b29e5d2d3538}" Title="S1 Nyan" RuntimeType="Silverlight" Version="1.1.0.0" Genre="apps.normal" Author="Obi Wang" Description="Sample description" Publisher="Obi Wang" BitsPerPixel="32">
    <IconPath IsRelative="true" IsResource="false">ApplicationIcon.png</IconPath>
    <Capabilities>
      <Capability Name="ID_CAP_NETWORKING" />
    </Capabilities>
    <Tasks>
      <DefaultTask Name="_default" NavigationPage="Views\MainPage.xaml" />
    </Tasks>
    <Tokens>
      <PrimaryToken TokenID="S1Nyan.AppToken" TaskName="_default">
        <TemplateType5>
          <BackgroundImageURI IsRelative="true" IsResource="false">Background.png</BackgroundImageURI>
          <Count>0</Count>
          <Title>S1 Nyan</Title>
        </TemplateType5>
      </PrimaryToken>
    </Tokens>
  </App>
</Deployment>